{
  "main": {
    "id": "bd31b17ede14fad4",
    "type": "split",
    "children": [
      {
        "id": "9836c18b715a08d5",
        "type": "tabs",
        "dimension": 60.10745466756213,
        "children": [
          {
            "id": "62926372d0d4f34a",
            "type": "leaf",
            "state": {
              "type": "markdown",
              "state": {
                "file": "foreign trade/引爆外贸交易/一站式展会英语话术助力成交.md",
                "mode": "source",
                "source": false
              },
              "icon": "lucide-file",
              "title": "一站式展会英语话术助力成交"
            },
            "group": "f6a2ce5f730764c1"
          }
        ]
      },
      {
        "id": "7c92e592e735d2bc",
        "type": "tabs",
        "dimension": 39.89254533243788,
        "children": [
          {
            "id": "93f29e0db776684e",
            "type": "leaf",
            "state": {
              "type": "outline",
              "state": {
                "file": "foreign trade/引爆外贸交易/一站式展会英语话术助力成交.md",
                "followCursor": true,
                "showSearch": false,
                "searchQuery": ""
              },
              "icon": "lucide-list",
              "title": "一站式展会英语话术助力成交 的大纲"
            },
            "group": "f6a2ce5f730764c1"
          }
        ]
      }
    ],
    "direction": "vertical"
  },
  "left": {
    "id": "88ca7f98a5b28bd9",
    "type": "split",
    "children": [
      {
        "id": "62f6f5a4fe84aafb",
        "type": "tabs",
        "children": [
          {
            "id": "92fb039a56f20594",
            "type": "leaf",
            "state": {
              "type": "file-explorer",
              "state": {
                "sortOrder": "byCreatedTimeReverse",
                "autoReveal": false
              },
              "icon": "lucide-folder-closed",
              "title": "文件列表"
            }
          },
          {
            "id": "081a43316733d833",
            "type": "leaf",
            "state": {
              "type": "search",
              "state": {
                "query": "",
                "matchingCase": false,
                "explainSearch": false,
                "collapseAll": false,
                "extraContext": false,
                "sortOrder": "alphabetical"
              },
              "icon": "lucide-search",
              "title": "搜索"
            }
          },
          {
            "id": "a6c455c90d54268d",
            "type": "leaf",
            "state": {
              "type": "bookmarks",
              "state": {},
              "icon": "lucide-bookmark",
              "title": "书签"
            }
          },
          {
            "id": "4173295fa23da529",
            "type": "leaf",
            "state": {
              "type": "calendar",
              "state": {},
              "icon": "calendar-with-checkmark",
              "title": "Calendar"
            }
          }
        ]
      }
    ],
    "direction": "horizontal",
    "width": 300
  },
  "right": {
    "id": "5989f8b9a5320ef1",
    "type": "split",
    "children": [
      {
        "id": "72964fd27eeb16bc",
        "type": "tabs",
        "children": [
          {
            "id": "c796ff84bf8bbd08",
            "type": "leaf",
            "state": {
              "type": "backlink",
              "state": {
                "collapseAll": false,
                "extraContext": false,
                "sortOrder": "alphabetical",
                "showSearch": false,
                "searchQuery": "",
                "backlinkCollapsed": false,
                "unlinkedCollapsed": true
              },
              "icon": "links-coming-in",
              "title": "反向链接"
            }
          },
          {
            "id": "8afda015b35c2bb4",
            "type": "leaf",
            "state": {
              "type": "outgoing-link",
              "state": {
                "linksCollapsed": false,
                "unlinkedCollapsed": true
              },
              "icon": "links-going-out",
              "title": "出链"
            }
          },
          {
            "id": "2048b9dca962442a",
            "type": "leaf",
            "state": {
              "type": "tag",
              "state": {
                "sortOrder": "frequency",
                "useHierarchy": true,
                "showSearch": false,
                "searchQuery": ""
              },
              "icon": "lucide-tags",
              "title": "标签"
            }
          },
          {
            "id": "cc5cd2a0d8d54d8c",
            "type": "leaf",
            "state": {
              "type": "outline",
              "state": {
                "file": "foreign trade/引爆外贸交易/一站式展会英语话术助力成交.md",
                "followCursor": false,
                "showSearch": false,
                "searchQuery": ""
              },
              "icon": "lucide-list",
              "title": "一站式展会英语话术助力成交 的大纲"
            }
          },
          {
            "id": "9df26eefbebf15ef",
            "type": "leaf",
            "state": {
              "type": "git-view",
              "state": {},
              "icon": "git-pull-request",
              "title": "Source Control"
            }
          },
          {
            "id": "ad25169f0c9eb315",
            "type": "leaf",
            "state": {
              "type": "all-properties",
              "state": {
                "sortOrder": "frequency",
                "showSearch": false,
                "searchQuery": ""
              },
              "icon": "lucide-archive",
              "title": "添加笔记属性"
            }
          },
          {
            "id": "de78c82773449aa9",
            "type": "leaf",
            "state": {
              "type": "advanced-tables-toolbar",
              "state": {},
              "icon": "spreadsheet",
              "title": "Advanced Tables"
            }
          }
        ],
        "currentTab": 4
      }
    ],
    "direction": "horizontal",
    "width": 327.5,
    "collapsed": true
  },
  "left-ribbon": {
    "hiddenItems": {
      "graph:查看关系图谱": false,
      "obsidian-git:Open Git source control": false,
      "obsidian-kanban:创建新看板": false,
      "switcher:打开快速切换": false,
      "canvas:新建白板": false,
      "templates:插入模板": false,
      "table-editor-obsidian:Advanced Tables Toolbar": false,
      "templater-obsidian:Templater": false,
      "command-palette:打开命令面板": false,
      "obsidian-excalidraw-plugin:新建绘图文件": false
    }
  },
  "active": "62926372d0d4f34a",
  "lastOpenFiles": [
    "foreign trade/引爆外贸交易/客户拜访接待话术让订单无处可逃.md",
    "foreign trade/引爆外贸交易/一站式展会英语话术助力成交.md",
    "foreign trade/引爆外贸交易/任务集合.md",
    "foreign trade/引爆外贸交易/外贸谈资.md",
    "foreign trade/引爆外贸交易/复盘十天成交$230 万订单.md",
    "Excalidraw/Drawing 2025-07-01 11.41.07.excalidraw.md",
    "Excalidraw/Drawing 2025-06-25 15.56.14.excalidraw.md",
    "Excalidraw/Drawing 2025-07-01 11.38.05.excalidraw.md",
    "未命名.canvas",
    "每日TODO/日常任务.md",
    "2025-06-25.md",
    "Excalidraw",
    "外贸谈资.md",
    "外贸谈资 @{2025-06-25}.md",
    "foreign trade/引爆外贸交易",
    "未命名.md",
    "每日TODO/2025-06-25.md",
    "每日TODO",
    "未命名看板.md",
    "foreign trade",
    "创建链接.md",
    "欢迎.md"
  ]
}